ethaddrlib/__init__.py
ethaddrlib/core.py
ethaddrlib-0.1.1.dist-info/METADATA
ethaddrlib-0.1.1.dist-info/WHEEL
ethaddrlib-0.1.1.dist-info/top_level.txt
ethaddrlib-0.1.1.dist-info/RECORD
